GoogleCloudPlatformAPI/AdManager.py
GoogleCloudPlatformAPI/Analytics.py
GoogleCloudPlatformAPI/BigQuery.py
GoogleCloudPlatformAPI/CloudStorage.py
GoogleCloudPlatformAPI/Oauth.py
GoogleCloudPlatformAPI/Utils.py
GoogleCloudPlatformAPI/__init__.py
googlecloudplatformapi-2.3.6.dist-info/licenses/LICENSE
googlecloudplatformapi-2.3.6.dist-info/METADATA
googlecloudplatformapi-2.3.6.dist-info/WHEEL
googlecloudplatformapi-2.3.6.dist-info/top_level.txt
googlecloudplatformapi-2.3.6.dist-info/RECORD
